Metadata-Version: 2.1
Name: config2colander
Version: 1.0
Summary: create a deform/colander schema from json configuration
Home-page: http://www.pingpongstars.it
Author: pdepmcp
Author-email: pdepmcp@gmail.com
License: MIT
Keywords: pyramid module deform/colander schema
Platform: UNKNOWN
Classifier: Development Status :: 5 - Production/Stable
Classifier: Intended Audience :: Developers
Classifier: Operating System :: OS Independent
Classifier: Programming Language :: Python :: 3.9
Requires-Python: >=3.7
